gpb_models/PKG-INFO
gpb_models/README.md
gpb_models/__init__.py
gpb_models/dist/gpb_models-1.4.4.tar.gz
gpb_models/models.py
gpb_models/pyproject.toml
gpb_models/types.py
gpb_models-1.4.4.dist-info/METADATA
gpb_models-1.4.4.dist-info/WHEEL
gpb_models-1.4.4.dist-info/RECORD
