Metadata-Version: 2.4
Name: gpb-models
Version: 1.4.4
Summary: Pydantic datamodels for the Gene Panel Builder
License-Expression: GPL-3.0-or-later
Requires-Python: >=3.8,<4.0
Classifier: Programming Language :: Python :: 3
Classifier: Programming Language :: Python :: 3.8
Classifier: Programming Language :: Python :: 3.9
Classifier: Programming Language :: Python :: 3.10
Classifier: Programming Language :: Python :: 3.11
Classifier: Programming Language :: Python :: 3.12
Classifier: Programming Language :: Python :: 3.13
Classifier: Programming Language :: Python :: 3.14
Requires-Dist: pydantic (>=2.10.6,<3.0.0)
Project-URL: Homepage, https://gitlab.com/alleles/genepanel-builder
Project-URL: Repository, https://gitlab.com/alleles/genepanel-builder
